dmSQLAlchemy/__init__.py
dmSQLAlchemy/base.py
dmSQLAlchemy/dmPython.py
dmSQLAlchemy/json.py
dmSQLAlchemy/types.py
dmsqlalchemy-2.0.6.dist-info/licenses/LICENSE
dmsqlalchemy-2.0.6.dist-info/METADATA
dmsqlalchemy-2.0.6.dist-info/WHEEL
dmsqlalchemy-2.0.6.dist-info/entry_points.txt
dmsqlalchemy-2.0.6.dist-info/top_level.txt
dmsqlalchemy-2.0.6.dist-info/RECORD
