Metadata-Version: 2.4
Name: dmSQLAlchemy
Version: 2.0.6
Summary: SQLAlchemy dialect for DM
Author: Dameng
Author-email: 
Keywords: DM SQLAlchemy
License-File: LICENSE
Requires-Dist: dmPython
Requires-Dist: sqlalchemy>1.4.54
Dynamic: author
Dynamic: keywords
Dynamic: license-file
Dynamic: requires-dist
Dynamic: summary
